puddl/__init__.py
puddl/conf.py
puddl/djangomodels.py
puddl/exc.py
puddl/typing.py
puddl/audio/__init__.py
puddl/audio/cli.py
puddl/bash_history/__init__.py
puddl/bash_history/parser.py
puddl/cli/__init__.py
puddl/cli/base.py
puddl/cli/config.py
puddl/cli/db.py
puddl/codimd/__init__.py
puddl/codimd/api.py
puddl/codimd/index.py
puddl/codimd/models.py
puddl/codimd/run.py
puddl/db/__init__.py
puddl/db/alchemy.py
puddl/db/tool.py
puddl/exif/__init__.py
puddl/exif/app.py
puddl/exif/load.py
puddl/exif/rotations.py
puddl/exif/test.py
puddl/felix/__init__.py
puddl/felix/codimd/__init__.py
puddl/felix/codimd/cli.py
puddl/felix/codimd/index.py
puddl/felix/codimd/models.py
puddl/felix/file/__init__.py
puddl/felix/file/cli.py
puddl/felix/file/db.py
puddl/felix/file/lib.py
puddl/felix/git/__init__.py
puddl/felix/git/app.py
puddl/felix/git/cli.py
puddl/felix/git/conftest.py
puddl/felix/git/repo2rows.py
puddl/felix/git/test.py
puddl/felix/git/utils.py
puddl/felix/jsonlines/__init__.py
puddl/felix/mampf/__init__.py
puddl/felix/mampf/cli.py
puddl/felix/mampf/models.py
puddl/pg/__init__.py
puddl/pg/db.py
puddl/pg/utils.py
puddl/speech/__init__.py
puddl/speech/cli.py
puddl/tests/__init__.py
puddl/tests/test_alchemy.py
puddl/tests/test_bash_history.py
puddl/tests/test_conf.py
puddl/tests/test_handle_psycopg2_errors.py
puddl/tests/test_pg.py
puddl/video/__init__.py
puddl/video/thumbnails.py
puddl-0.10.0.data/scripts/mail-spam-per-addr.py
puddl-0.10.0.data/scripts/puddl-adb-contacts
puddl-0.10.0.data/scripts/puddl-adb-list-packages
puddl-0.10.0.data/scripts/puddl-adb-wifi
puddl-0.10.0.data/scripts/puddl-audio-remove-silence
puddl-0.10.0.data/scripts/puddl-cached-db-url
puddl-0.10.0.data/scripts/puddl-curl
puddl-0.10.0.data/scripts/puddl-exif-extract-usercomment
puddl-0.10.0.data/scripts/puddl-git-api-documentation-generator
puddl-0.10.0.data/scripts/puddl-git-repo-find
puddl-0.10.0.data/scripts/puddl-git-uri
puddl-0.10.0.data/scripts/puddl-html-css-select
puddl-0.10.0.dist-info/LICENSE
puddl-0.10.0.dist-info/METADATA
puddl-0.10.0.dist-info/WHEEL
puddl-0.10.0.dist-info/entry_points.txt
puddl-0.10.0.dist-info/top_level.txt
puddl-0.10.0.dist-info/RECORD
