Metadata-Version: 2.1
Name: puddl
Version: 0.10.0
Home-page: https://puddl.org
Author: Felix Hummel
Author-email: puddl-dev@felixhummel.de
License-File: LICENSE
Requires-Dist: click
Requires-Dist: psycopg2-binary
Requires-Dist: pydantic
Requires-Dist: structlog
Provides-Extra: dev
Requires-Dist: black ; extra == 'dev'
Requires-Dist: bumpversion ; extra == 'dev'
Requires-Dist: flake8 ; extra == 'dev'
Requires-Dist: pip-tools ; extra == 'dev'
Requires-Dist: pytest ; extra == 'dev'
Requires-Dist: twine ; extra == 'dev'
Provides-Extra: full
Requires-Dist: filetype ; extra == 'full'
Requires-Dist: flask ; extra == 'full'
Requires-Dist: pandas ; extra == 'full'
Requires-Dist: python-dotenv ; extra == 'full'
Requires-Dist: requests ; extra == 'full'
Requires-Dist: sqlalchemy ; extra == 'full'
Requires-Dist: tinytag ; extra == 'full'
Provides-Extra: stt
Requires-Dist: openai-whisper ; extra == 'stt'
